Metadata-Version: 2.1
Name: datasette-render-binary
Version: 0.3.1
Summary: Datasette plugin for rendering binary data
Home-page: https://datasette.io/plugins/datasette-render-binary
Author: Simon Willison
License: Apache License, Version 2.0
Project-URL: Issues, https://github.com/simonw/datasette-render-binary/issues
Project-URL: CI, https://github.com/simonw/datasette-render-binary/actions
Project-URL: Changelog, https://github.com/simonw/datasette-render-binary/releases
Classifier: Framework :: Datasette
Classifier: License :: OSI Approved :: Apache Software License
Requires-Python: >=3.7
License-File: LICENSE
Requires-Dist: datasette
Requires-Dist: filetype
Provides-Extra: test
Requires-Dist: pytest ; extra == 'test'
